{
  "clientes": [
    {
      "id": 1,
      "nombre": "Rita Corpus"
    },
    {
      "id": 2,
      "nombre": "David Martinez"
    },
    {
      "id": 3,
      "nombre": "Sebastian Martinez"
    },
    {
      "id": 4,
      "nombre": "Juan Perez"
    }
  ],
  "vehiculos": [
    {
      "id": 1,
      "clienteId": 1,
      "nombre": "Crossfox 2009"
    },
    {
      "id": 2,
      "clienteId": 2,
      "nombre": "Tsuru 2008"
    },
    {
      "id": 3,
      "clienteId": 2,
      "nombre": "Accord 2005"
    },
    {
      "id": 4,
      "clienteId": 1,
      "nombre": "Beetle 2006"
    },
    {
      "id": 5,
      "clienteId": 3,
      "nombre": "Mazda RX7 2001"
    },
    {
      "id": 6,
      "clienteId": 1,
      "nombre": "Sonic 2012"
    },
    {
      "id": 7,
      "clienteId": 2,
      "nombre": "VW VOCHO 2001"
    },
    {
      "id": 8,
      "clienteId": 4,
      "nombre": "Chevy 1999"
    }
  ],
  "servicios": [
    {
      "id": 1,
      "vehiculoId": 1,
      "tipo": "Inspeccion"
    },
    {
      "id": 2,
      "vehiculoId": 2,
      "tipo": "Cambio de aceite"
    },
    {
      "id": 3,
      "vehiculoId": 3,
      "tipo": "Afinacion Mayor"
    },
    {
      "id": 4,
      "vehiculoId": 4,
      "tipo": "Cambio de balatas"
    },
    {
      "id": 5,
      "vehiculoId": 5,
      "tipo": "Cambio de bujias"
    },
    {
      "id": 6,
      "vehiculoId": 6,
      "tipo": "Cambio de tapa de punterias"
    },
    {
      "id": 7,
      "vehiculoId": 7,
      "tipo": "Afinacion a motor"
    },
    {
      "id": 8,
      "vehiculoId": 8,
      "tipo": "Cambio de balatas"
    }
  ]
}